[
    {
        "date": "2026-02-23",
        "last_updated": "2026-02-23 22:32:16",
        "burn_xrp": 442,
        "load_usd_m": 2120,
        "transactions": 1.1,
        "tx_categories": {
            "settlement": 0.77,
            "identity": 0.165,
            "defi": 0.11,
            "acct_mgmt": 0.055
        },
        "load_categories": {
            "settlement": 1908.0,
            "identity": 42.4,
            "defi": 148.4,
            "acct_mgmt": 21.2
        },
        "is_fallback": false,
        "total_coins_xrp": null
    },
    {
        "date": "2026-02-24",
        "last_updated": "2026-02-24 23:39:02",
        "burn_xrp": null,
        "load_usd_m": null,
        "transactions": null,
        "tx_categories": {},
        "load_categories": {},
        "is_fallback": false,
        "total_coins_xrp": null
    },
    {
        "date": "2026-02-25",
        "last_updated": "2026-02-25 19:48:54",
        "open_coins_xrp": 99985704135.1659,
        "total_coins_xrp": 99985704101.56995,
        "burn_xrp": 33.595947,
        "load_usd_m": 2913.66,
        "transactions": 1.25,
        "tx_categories": {
            "settlement": 0.763,
            "identity": 0.0,
            "defi": 0.3491,
            "acct_mgmt": 0.1379
        },
        "load_categories": {
            "settlement": 1778.49,
            "identity": 0.0,
            "defi": 813.79,
            "acct_mgmt": 321.38
        },
        "is_fallback": false,
        "is_partial": true,
        "partial_as_of": "19:48"
    }
]